juneberry/__init__.py
juneberry/_callers.py
juneberry/_levels.py
juneberry/_loggers.py
juneberry/_timestamps.py
juneberry/ansi256/_beautify.py
juneberry/ansi256/_colors.py
juneberry/ansi256/_constants.py
juneberry/ansi256/_effects.py
juneberry/ansi256/_typehintings.py
juneberry/ansi256/themes/_default.py
juneberry/ansi256/themes/_theme.py
juneberry-1.4.0.dist-info/LICENSE
juneberry-1.4.0.dist-info/METADATA
juneberry-1.4.0.dist-info/WHEEL
juneberry-1.4.0.dist-info/RECORD
